LICENSE.txt
MANIFEST.in
README.rst
setup.cfg
setup.py
versioneer.py
bin/nanshe-converter
bin/nanshe-learner
bin/nanshe-registerer
nanshe/__init__.py
nanshe/_version.py
nanshe/converter.py
nanshe/learner.py
nanshe/registerer.py
nanshe.egg-info/PKG-INFO
nanshe.egg-info/SOURCES.txt
nanshe.egg-info/dependency_links.txt
nanshe.egg-info/top_level.txt
nanshe.egg-info/zip-safe
nanshe/box/__init__.py
nanshe/box/spams_sandbox.py
nanshe/imp/__init__.py
nanshe/imp/registration.py
nanshe/imp/renorm.py
nanshe/imp/segment.py
nanshe/imp/filters/__init__.py
nanshe/imp/filters/masks.py
nanshe/imp/filters/noise.py
nanshe/imp/filters/wavelet.py
nanshe/io/__init__.py
nanshe/io/xjson.py
nanshe/io/xtiff.py
nanshe/io/hdf5/__init__.py
nanshe/io/hdf5/record.py
nanshe/io/hdf5/search.py
nanshe/io/hdf5/serializers.py
nanshe/misc/__init__.py
nanshe/misc/neuron_matplotlib_viewer.py
nanshe/misc/random_dictionary_learning_data.py
nanshe/syn/__init__.py
nanshe/syn/data.py
nanshe/util/__init__.py
nanshe/util/iters.py
nanshe/util/prof.py
nanshe/util/wrappers.py
nanshe/util/xglob.py
nanshe/util/xnumpy.py