Metadata-Version: 1.0
Name: nanshe
Version: 0.1.0a60
Summary: An image processing toolkit.
Home-page: https://github.com/nanshe-org/nanshe
Author: John Kirkham
Author-email: kirkhamj@janelia.hhmi.org
License: BSD 3-Clause
Platform: UNKNOWN
